poai/__init__.py
poai/api/__init__.py
poai/api/aiart.py
poai/api/chat.py
poai/api/chatgpt.py
poai/core/AIArt.py
poai/core/TongYi.py
poai/core/ZhiPu.py
poai/core/__init__.py
poai/lib/Const.py
poai/lib/__init__.py
tests/__init__.py
tests/test_chat.py
tests/test_tools.py
poai-0.0.11.dist-info/LICENSE
poai-0.0.11.dist-info/METADATA
poai-0.0.11.dist-info/WHEEL
poai-0.0.11.dist-info/top_level.txt
poai-0.0.11.dist-info/RECORD
