Metadata-Version: 2.1
Name: poai
Version: 0.0.11
Summary: pip install poai
Home-page: https://www.python-office.com/
Author: CoderWanFeng
Author-email: 1957875073@qq.com
License: MIT
Project-URL: Bug Tracker, https://github.com/CoderWanFeng/poai/issues
Project-URL: Documentation, https://github.com/CoderWanFeng/poai/blob/main/README.md
Project-URL: Source Code, https://github.com/CoderWanFeng/poai
Platform: any
Requires-Python: >=3.7
License-File: LICENSE
Requires-Dist: openai
Requires-Dist: Pillow
Requires-Dist: tencentcloud-sdk-python
Requires-Dist: zhipuai
